MANIFEST.in
README.md
Requirements.txt
setup.py
Blogging_Plugins.egg-info/PKG-INFO
Blogging_Plugins.egg-info/SOURCES.txt
Blogging_Plugins.egg-info/dependency_links.txt
Blogging_Plugins.egg-info/not-zip-safe
Blogging_Plugins.egg-info/requires.txt
Blogging_Plugins.egg-info/top_level.txt
blogging_plugins/__init__.py
blogging_plugins/posts_flow/README.md
blogging_plugins/posts_flow/__init__.py
blogging_plugins/summary/README.md
blogging_plugins/summary/__init__.py
blogging_plugins/tag_cloud/README.md
blogging_plugins/tag_cloud/__init__.py
tests/__init__.py